{"pln":[{"name":"dishub","url":"dishub.kaltimprov.go.id"}],"data":[{"title":"Gunung Manggah","samagov":"T-iKqe8aWXsmhbBcpZowp"},{"title":"Jembatan Sei Dama","samagov":"GmnDjQ2Ah6MpdznbtazD-"},{"title":"JLN Sultan Sulaiman SMD","pln":"dishub","cameraId":"1836","camId":"4xIx1DNLTjM0T000NTJNM9FLTsw1MBAS2HZXf9mRQCfG9RXFqo9ncCwHAA"},{"title":"Simpang Tempekong","samagov":"EcsSwEXnhGjkxpYsK50Gf"},{"title":"Sungai Dama SMD","pln":"dishub","cameraId":"1827","camId":"4xIx1DNLTjM0T000NTJNM9BLTsw1MBAS2HZXf9mRQCfG9RXFqo9ncCwHAA"},{"title":"TPS Gunung Manggah","samagov":"OYR4wVc4RQrldL7Ykgbnt"},{"title":"TPS Jelawat","samagov":"_7xUXvdSR3kfwux9zfGHM"}]}
